directory_schema/__init__.py
directory_schema/__main__.py
directory_schema/cli.py
directory_schema/directory_schema.py
directory_schema/errors.py
directory_schema/py.typed
directory_schema-0.0.2.dist-info/LICENSE
directory_schema-0.0.2.dist-info/METADATA
directory_schema-0.0.2.dist-info/WHEEL
directory_schema-0.0.2.dist-info/entry_points.txt
directory_schema-0.0.2.dist-info/top_level.txt
directory_schema-0.0.2.dist-info/RECORD
