Metadata-Version: 2.1
Name: directory-schema
Version: 0.0.2
Summary: Use JSON Schema to validate directory structures
Home-page: https://github.com/hubmapconsortium/directory-schema
Author: C McCallum
Author-email: mccallucc@gmail.com
License: MIT license
Keywords: directory_schema
Platform: UNKNOWN
Classifier: Development Status :: 2 - Pre-Alpha
Classifier: License :: OSI Approved :: MIT License
Classifier: Natural Language :: English
Classifier: Programming Language :: Python :: 3
Requires-Python: >=3.6
Requires-Dist: jsonschema
Requires-Dist: pyyaml
